pystreams-0.6.dist-info/top_level.txt
pystreams-0.6.dist-info/WHEEL
pystreams-0.6.dist-info/pydist.json
pystreams-0.6.dist-info/zip-safe
pystreams-0.6.dist-info/METADATA
pystreams-0.6.dist-info/RECORD
pystreams-0.6.dist-info/DESCRIPTION.rst
streams/poolofpools.py
streams/utils.py
streams/__init__.py
streams/iterators.py
streams/stream.py
streams/executors/executors.py
streams/executors/mixins.py
streams/executors/__init__.py
streams/executors/gevent.py
